{"name":"build-javascript","namedChunkGroups":{"polyfill":{"name":"polyfill","assets":[{"name":"webpack-runtime-c9459c9c69097daebbae.js","size":3308},{"name":"polyfill-fdd527c6ce466fa3ef3d.js","size":85840}],"filteredAssets":0,"assetsSize":89148,"filteredAuxiliaryAssets":2,"auxiliaryAssetsSize":221381},"app":{"name":"app","assets":[{"name":"webpack-runtime-c9459c9c69097daebbae.js","size":3308},{"name":"framework-efd0a41842175d0ccd97.js","size":22266},{"name":"styles.d2d43f20ec9a16bd97ae.css","size":38834},{"name":"app-e693e6dd0a5722cb0b4d.js","size":53470}],"filteredAssets":0,"assetsSize":117878,"filteredAuxiliaryAssets":5,"auxiliaryAssetsSize":359670},"component---src-pages-404-tsx":{"name":"component---src-pages-404-tsx","assets":[{"name":"commons-4314f0a16a27b0b9faeb.js","size":18831},{"name":"component---src-pages-404-tsx-4613e7dccddc982d4631.js","size":722}],"filteredAssets":0,"assetsSize":19553,"filteredAuxiliaryAssets":2,"auxiliaryAssetsSize":74237},"component---src-pages-index-tsx":{"name":"component---src-pages-index-tsx","assets":[{"name":"commons-4314f0a16a27b0b9faeb.js","size":18831},{"name":"component---src-pages-index-tsx-f49d294db15c1a77f965.js","size":3145}],"filteredAssets":0,"assetsSize":21976,"filteredAuxiliaryAssets":2,"auxiliaryAssetsSize":82164}},"assetsByChunkName":{"polyfill":["webpack-runtime-c9459c9c69097daebbae.js","polyfill-fdd527c6ce466fa3ef3d.js"],"app":["webpack-runtime-c9459c9c69097daebbae.js","framework-efd0a41842175d0ccd97.js","styles.d2d43f20ec9a16bd97ae.css","app-e693e6dd0a5722cb0b4d.js"],"component---src-pages-404-tsx":["commons-4314f0a16a27b0b9faeb.js","component---src-pages-404-tsx-4613e7dccddc982d4631.js"],"component---src-pages-index-tsx":["commons-4314f0a16a27b0b9faeb.js","component---src-pages-index-tsx-f49d294db15c1a77f965.js"]},"childAssetsByChunkName":{}}